morph/__init__.py
morph/cli/README.md
morph/cli/__init__.py
morph/cli/flags.py
morph/cli/main.py
morph/cli/params.py
morph/cli/requires.py
morph/cli/types.py
morph/config/__init__.py
morph/config/project.py
morph/constants.py
morph/py.typed
morph/task/__init__.py
morph/task/base.py
morph/task/compile.py
morph/task/init.py
morph/task/new.py
morph/task/resource.py
morph/task/run.py
morph/task/template/.gitignore
morph/task/template/cells/__init__.py
morph/task/template/cells/api/__init__.py
morph/task/template/cells/api/create_table.py
morph/task/template/cells/api/execute_sql.py
morph/task/template/cells/api/generate_report.py
morph/task/template/cells/api/get_data_path.py
morph/task/template/cells/api/get_file.py
morph/task/template/cells/api/insert_records.py
morph/task/template/cells/api/load_data.py
morph/task/template/cells/api/read_dir.py
morph/task/template/cells/api/ref.py
morph/task/template/cells/api/send_email.py
morph/task/template/cells/api/update_records.py
morph/task/template/cells/example_python_cell.py
morph/task/template/cells/example_sql_cell.sql
morph/task/template/data/World_Average_Temperature_2020_2024.csv
morph/task/template/en/README.md
morph/task/template/en/README_knowledge.md
morph/task/template/ja/README.md
morph/task/template/ja/README_knowledge.md
morph/task/template/pyproject.toml
morph/task/template/templates/prompt/README.md
morph/task/template/templates/python/README.md
morph/task/template/templates/sql/README.md
morph/task/template/templates/template.yaml
morph/task/utils/__init__.py
morph/task/utils/connections/bigquery/api.py
morph/task/utils/connections/bigquery/types.py
morph/task/utils/connections/bigquery/usecase.py
morph/task/utils/connections/connector.py
morph/task/utils/connections/database/mysql.py
morph/task/utils/connections/database/postgres.py
morph/task/utils/connections/database/redshift.py
morph/task/utils/connections/database/types.py
morph/task/utils/connections/snowflake/api.py
morphdb_utils-0.2.53.dist-info/METADATA
morphdb_utils-0.2.53.dist-info/WHEEL
morphdb_utils-0.2.53.dist-info/entry_points.txt
morphdb_utils-0.2.53.dist-info/RECORD
