Metadata-Version: 2.1
Name: morphdb-utils
Version: 0.2.53
Summary: 
Author: Morph
Author-email: contact@morphdb.io
Requires-Python: >=3.9,<4.0
Classifier: Programming Language :: Python :: 3
Classifier: Programming Language :: Python :: 3.9
Classifier: Programming Language :: Python :: 3.10
Classifier: Programming Language :: Python :: 3.11
Classifier: Programming Language :: Python :: 3.12
Provides-Extra: morph-project
Requires-Dist: Jinja2 (>=3.1.4,<4.0.0)
Requires-Dist: aiomysql (>=0.2.0,<0.3.0)
Requires-Dist: asyncpg (>=0.29.0,<0.30.0)
Requires-Dist: aws-lambda-powertools (>=2.34.2,<3.0.0) ; extra == "morph-project"
Requires-Dist: boto3 (>=1.26.80,<2.0.0) ; extra == "morph-project"
Requires-Dist: click (>=8.1.7,<9.0.0)
Requires-Dist: colorlog (>=6.8.2,<7.0.0)
Requires-Dist: cryptography (>=42.0.8,<43.0.0)
Requires-Dist: duckdb (>=1.0.0,<2.0.0)
Requires-Dist: google (>=3.0.0,<4.0.0)
Requires-Dist: google-api-python-client (>=2.139.0,<3.0.0)
Requires-Dist: google-cloud-bigquery (>=3.25.0,<4.0.0)
Requires-Dist: greenlet (>=3.0.3,<4.0.0)
Requires-Dist: gspread (>=6.1.2,<7.0.0)
Requires-Dist: kaleido (==0.2.1) ; extra == "morph-project"
Requires-Dist: line-profiler (>=4.1.2,<5.0.0) ; extra == "morph-project"
Requires-Dist: matplotlib (==3.5.2) ; extra == "morph-project"
Requires-Dist: openpyxl (>=3.1.2,<4.0.0) ; extra == "morph-project"
Requires-Dist: pandas (==2.1.3) ; extra == "morph-project"
Requires-Dist: paramiko (>=3.4.0,<4.0.0)
Requires-Dist: plotly (>=5.18.0,<6.0.0) ; extra == "morph-project"
Requires-Dist: psycopg2-binary (>=2.9.9,<3.0.0)
Requires-Dist: pyarrow (>=17.0.0,<18.0.0)
Requires-Dist: pydantic (>=2.5.3,<3.0.0) ; extra == "morph-project"
Requires-Dist: pyjwt (>=2.8.0,<3.0.0)
Requires-Dist: pypdf2 (>=3.0.1,<4.0.0)
Requires-Dist: pypika (>=0.48.9,<0.49.0) ; extra == "morph-project"
Requires-Dist: pyppeteer (>=2.0.0,<3.0.0) ; extra == "morph-project"
Requires-Dist: python-dotenv (>=1.0.1,<2.0.0)
Requires-Dist: pyyaml (>=6.0.1,<7.0.0)
Requires-Dist: requests (==2.31.0) ; extra == "morph-project"
Requires-Dist: seaborn (>=0.13.2,<0.14.0) ; extra == "morph-project"
Requires-Dist: simplejson (>=3.19.2,<4.0.0) ; extra == "morph-project"
Requires-Dist: snowflake-connector-python (>=3.11.0,<4.0.0)
Requires-Dist: sqlalchemy (==1.4.52)
Requires-Dist: sqlalchemy-redshift (>=0.8.14,<0.9.0)
Requires-Dist: sqlparse (>=0.4.4,<0.5.0) ; extra == "morph-project"
Requires-Dist: sshtunnel (>=0.4.0,<0.5.0)
Requires-Dist: toml (>=0.10.2,<0.11.0)
Requires-Dist: urllib3 (==1.26.18) ; extra == "morph-project"
Requires-Dist: xlrd (==2.0.1) ; extra == "morph-project"
